pynauty/__init__.py
pynauty/__main__.py
pynauty/graph.py
pynauty/nautywrap.c
pynauty/nautywrap.cpython-310-x86_64-linux-gnu.so
pynauty/nautywrap.h
pynauty/__pycache__/__init__.cpython-310.pyc
pynauty/__pycache__/graph.cpython-310.pyc
pynauty/docs/doctrees/environment.pickle
pynauty/docs/doctrees/guide.doctree
pynauty/docs/doctrees/index.doctree
pynauty/docs/doctrees/install.doctree
pynauty/docs/doctrees/intro.doctree
pynauty/docs/html/.buildinfo
pynauty/docs/html/genindex.html
pynauty/docs/html/guide.html
pynauty/docs/html/index.html
pynauty/docs/html/install.html
pynauty/docs/html/intro.html
pynauty/docs/html/objects.inv
pynauty/docs/html/py-modindex.html
pynauty/docs/html/search.html
pynauty/docs/html/searchindex.js
pynauty/docs/html/_modules/index.html
pynauty/docs/html/_modules/pynauty.html
pynauty/docs/html/_modules/pynauty/graph.html
pynauty/docs/html/_sources/guide.rst.txt
pynauty/docs/html/_sources/index.rst.txt
pynauty/docs/html/_sources/install.rst.txt
pynauty/docs/html/_sources/intro.rst.txt
pynauty/docs/html/_static/_sphinx_javascript_frameworks_compat.js
pynauty/docs/html/_static/basic.css
pynauty/docs/html/_static/classic.css
pynauty/docs/html/_static/doctools.js
pynauty/docs/html/_static/documentation_options.js
pynauty/docs/html/_static/file.png
pynauty/docs/html/_static/jquery-3.6.0.js
pynauty/docs/html/_static/jquery.js
pynauty/docs/html/_static/language_data.js
pynauty/docs/html/_static/minus.png
pynauty/docs/html/_static/plus.png
pynauty/docs/html/_static/pygments.css
pynauty/docs/html/_static/searchtools.js
pynauty/docs/html/_static/sidebar.js
pynauty/docs/html/_static/sphinx_highlight.js
pynauty/docs/html/_static/underscore-1.13.1.js
pynauty/docs/html/_static/underscore.js
pynauty/tests/conftest.py
pynauty/tests/test_autgrp.py
pynauty/tests/test_isomorphic.py
pynauty/tests/test_minimal.py
pynauty-2.8.6.dist-info/COPYING
pynauty-2.8.6.dist-info/METADATA
pynauty-2.8.6.dist-info/WHEEL
pynauty-2.8.6.dist-info/top_level.txt
pynauty-2.8.6.dist-info/RECORD
