Metadata-Version: 2.1
Name: pynauty
Version: 2.8.6
Summary: Isomorphism testing and automorphisms of graphs.
Home-page: https://github.com/pdobsan/pynauty
Author: Peter Dobsan
Author-email: pdobsan@gmail.com
License: GNU General Public License v3
Platform: Linux
Platform: Unix
Platform: OS X
Classifier: Environment :: Console
Classifier: Operating System :: POSIX :: Linux
Classifier: Operating System :: Unix
Classifier: Programming Language :: Python
Classifier: Programming Language :: Python :: 3.7
Classifier: Programming Language :: Python :: 3.8
Classifier: Programming Language :: Python :: 3.9
Classifier: Programming Language :: Python :: 3.10
Classifier: Programming Language :: C
Classifier: Topic :: Scientific/Engineering
Classifier: Topic :: Scientific/Engineering :: Mathematics
Classifier: Intended Audience :: Science/Research
Classifier: Intended Audience :: Education
Classifier: License :: OSI Approved :: GNU General Public License v3 or later (GPLv3+)
License-File: COPYING
